<?xml version="1.0"?>
<menu>
  <item>
    <path>civicrm/mediwe/form/klant</path>
    <page_callback>CRM_Basis_Form_Klant</page_callback>
    <title>Klant</title>
    <access_arguments>access CiviCRM</access_arguments>
  </item>
  <item>
    <path>civicrm/mediwe/form/medewerker</path>
    <page_callback>CRM_Basis_Form_KlantMedewerker</page_callback>
    <title>Klant medewerker</title>
    <access_arguments>access CiviCRM</access_arguments>
  </item>
  <item>
    <path>civicrm/mediwe/form/controlearts</path>
    <page_callback>CRM_Basis_Form_ControleArts</page_callback>
    <title>Controlearts</title>
    <access_arguments>access CiviCRM</access_arguments>
  </item>
  <item>
    <path>civicrm/mediwe/form/inspecteur</path>
    <page_callback>CRM_Basis_Form_Inspecteur</page_callback>
    <title>Inspecteur</title>
    <access_arguments>access CiviCRM</access_arguments>
  </item>
  <item>
    <path>civicrm/mediwe/form/ziektemelding</path>
    <page_callback>CRM_Basis_Form_Ziektemelding</page_callback>
    <title>Ziektemelding</title>
    <access_arguments>access CiviCRM</access_arguments>
  </item>
  <item>
    <path>civicrm/mediwe/form/medischecontrole</path>
    <page_callback>CRM_Basis_Form_MedischeControle</page_callback>
    <title>Medische controle</title>
    <access_arguments>access CiviCRM</access_arguments>
  </item>
  <item>
    <path>civicrm/mediwe/printfaktuur</path>
    <page_callback>CRM_Basis_PrintFaktuur</page_callback>
    <title>Klant</title>
    <access_arguments>access CiviCRM</access_arguments>
  </item>
  <item>
    <path>civicrm/basis/page/testbasis</path>
    <page_callback>CRM_Basis_Page_TestBasis</page_callback>
    <title>TestBasis</title>
    <access_arguments>access CiviCRM</access_arguments>
  </item>
  <item>
    <path>civicrm/basis/page/ziektemelding</path>
    <page_callback>CRM_Basis_Page_Ziektemelding</page_callback>
    <title>Ziektemelding</title>
    <access_arguments>access CiviCRM</access_arguments>
  </item>
</menu>
